polars_network-0.0.3.dist-info/METADATA
polars_network-0.0.3.dist-info/WHEEL
polars_network/__init__.py
polars_network/__init__.pyi
polars_network/polars_network.abi3.so
polars_network/py.typed
polars_network-0.0.3.dist-info/RECORD
