Metadata-Version: 2.4
Name: polars-network
Version: 0.0.3
Classifier: Programming Language :: Rust
Classifier: Programming Language :: Python :: Implementation :: CPython
Classifier: Programming Language :: Python :: Implementation :: PyPy
Requires-Dist: maturin>=1.9.6
Requires-Dist: polars>=1.8.2
Requires-Python: >=3.8
